bluecat_libraries/__init__.py
bluecat_libraries/address_manager/__init__.py
bluecat_libraries/address_manager/version.py
bluecat_libraries/address_manager/api/__init__.py
bluecat_libraries/address_manager/api/_version.py
bluecat_libraries/address_manager/api/client.py
bluecat_libraries/address_manager/api/models.py
bluecat_libraries/address_manager/api/serialization.py
bluecat_libraries/address_manager/api/rest/__init__.py
bluecat_libraries/address_manager/api/rest/auto/__init__.py
bluecat_libraries/address_manager/api/rest/auto/_wadl_parser.py
bluecat_libraries/address_manager/api/rest/auto/client.py
bluecat_libraries/address_manager/api/rest/provisional/__init__.py
bluecat_libraries/address_manager/api/rest/provisional/client.py
bluecat_libraries/address_manager/api/rest/provisional/rest_dict.py
bluecat_libraries/address_manager/api/rest/provisional/rest_entity_array.py
bluecat_libraries/address_manager/api/rest/provisional/rest_fault.py
bluecat_libraries/address_manager/apiv2/__init__.py
bluecat_libraries/address_manager/apiv2/client.py
bluecat_libraries/address_manager/apiv2/constants.py
bluecat_libraries/address_manager/apiv2/exceptions.py
bluecat_libraries/address_manager/constants/__init__.py
bluecat_libraries/address_manager/constants/_enum.py
bluecat_libraries/address_manager/constants/_version.py
bluecat_libraries/address_manager/constants/access_right_values.py
bluecat_libraries/address_manager/constants/additional_ip_service_type.py
bluecat_libraries/address_manager/constants/defined_probe.py
bluecat_libraries/address_manager/constants/dhcp6_deployment_option_type.py
bluecat_libraries/address_manager/constants/dhcp_custom_option_type.py
bluecat_libraries/address_manager/constants/dhcp_define_range.py
bluecat_libraries/address_manager/constants/dhcp_deployment_role_type.py
bluecat_libraries/address_manager/constants/dhcp_match_class_criteria.py
bluecat_libraries/address_manager/constants/dhcp_service.py
bluecat_libraries-25.3.0.dist-info/licenses/LICENSE
bluecat_libraries-25.3.0.dist-info/METADATA
bluecat_libraries-25.3.0.dist-info/WHEEL
bluecat_libraries-25.3.0.dist-info/top_level.txt
bluecat_libraries-25.3.0.dist-info/RECORD
