Metadata-Version: 2.4
Name: bluecat-libraries
Version: 25.3.0
Summary: Modules for working with BlueCat products.
Home-page: https://docs.bluecatnetworks.com
Author: BlueCat
Maintainer: BlueCat
License: http://www.apache.org/licenses/LICENSE-2.0
Classifier: License :: OSI Approved :: Apache Software License
Classifier: Programming Language :: Python :: 3.11
Requires-Python: >=3.11.0
License-File: LICENSE
Requires-Dist: requests>=2.32.4
Provides-Extra: dev
Requires-Dist: pytest==7.3.0; extra == "dev"
Requires-Dist: responses==0.23.1; extra == "dev"
Requires-Dist: paramiko==3.0.0; extra == "dev"
Provides-Extra: internal-suds
Requires-Dist: suds-py3==1.4.5.0; extra == "internal-suds"
Dynamic: author
Dynamic: classifier
Dynamic: description
Dynamic: description-content-type
Dynamic: home-page
Dynamic: license
Dynamic: license-file
Dynamic: maintainer
Dynamic: provides-extra
Dynamic: requires-dist
Dynamic: requires-python
Dynamic: summary
